lava_top_sdk/__init__.py
lava_top_sdk/client.py
lava_top_sdk/config.py
lava_top_sdk/logger.py
lava_top_sdk/server.py
lava_top_sdk/types_custom.py
lava_top_sdk-1.1.1.dist-info/licenses/LICENSE
lava_top_sdk-1.1.1.dist-info/METADATA
lava_top_sdk-1.1.1.dist-info/WHEEL
lava_top_sdk-1.1.1.dist-info/top_level.txt
lava_top_sdk-1.1.1.dist-info/RECORD
