Metadata-Version: 2.4
Name: lava-top-sdk
Version: 1.1.1
Summary: Python client for Lava.top API
Author: LavaTop Team
License: MIT License
Project-URL: Homepage, https://lava.top
Project-URL: Documentation, https://gate.lava.top/docs
Project-URL: Repository, https://github.com/lava-top/python-sdk
Project-URL: Issues, https://github.com/lava-top/python-sdk/issues
Classifier: Development Status :: 4 - Beta
Classifier: Intended Audience :: Developers
Classifier: License :: OSI Approved :: MIT License
Classifier: Programming Language :: Python :: 3
Classifier: Programming Language :: Python :: 3.8
Classifier: Programming Language :: Python :: 3.9
Classifier: Programming Language :: Python :: 3.10
Classifier: Programming Language :: Python :: 3.11
Classifier: Programming Language :: Python :: 3.12
Requires-Python: >=3.8
License-File: LICENSE
Requires-Dist: requests>=2.31.0
Requires-Dist: pydantic>=2.5.0
Requires-Dist: python-dotenv>=1.0.0
Provides-Extra: dev
Requires-Dist: black>=23.0.0; extra == "dev"
Requires-Dist: pylint>=2.17.0; extra == "dev"
Requires-Dist: pytest>=7.4.0; extra == "dev"
Requires-Dist: pytest-cov>=4.1.0; extra == "dev"
Requires-Dist: pytest-asyncio>=0.21.0; extra == "dev"
Provides-Extra: examples
Requires-Dist: fastapi>=0.104.0; extra == "examples"
Requires-Dist: uvicorn>=0.24.0; extra == "examples"
Dynamic: license-file
